<?xml version='1.0' encoding='UTF-8'?>
<economycore>
    <classes>
        <rootclass name="DefaultWeapon" />
        <rootclass name="DefaultMagazine" />
        <rootclass name="Inventory_Base" />
        <rootclass name="HouseNoDestruct" reportMemoryLOD="no" />
        <rootclass name="SurvivorBase" act="character" reportMemoryLOD="no" />
        <rootclass name="DZ_LightAI" act="character" reportMemoryLOD="no" />
        <rootclass name="CarScript" act="car" reportMemoryLOD="no" />
    </classes>
    <defaults>
        <default name="dyn_radius" value="30" />
        <default name="dyn_smin" value="0" />
        <default name="dyn_smax" value="0" />
        <default name="dyn_dmin" value="1" />
        <default name="dyn_dmax" value="5" />
        <default name="log_ce_loop" value="false" />
        <default name="log_ce_dynamicevent" value="true" />
        <default name="log_ce_vehicle" value="false" />
        <default name="log_ce_lootspawn" value="false" />
        <default name="log_ce_lootcleanup" value="false" />
        <default name="log_ce_lootrespawn" value="false" />
        <default name="log_ce_statistics" value="true" />
        <default name="log_ce_zombie" value="true" />
        <default name="log_storageinfo" value="false" />
        <default name="log_hivewarning" value="true" />
        <default name="log_missionfilewarning" value="true" />
        <default name="save_events_startup" value="true" />
        <default name="save_types_startup" value="true" />
        <default name="randomloot_deloot_perevent" value="6" />
    </defaults>
    <ce folder="jmc_ce">
        <file name="types_jmc.xml" type="types" />
    </ce>

	<ce folder="expansion_ce">
		<file name="expansion_types.xml" type="types" />
		<file name="expansion_spawnabletypes.xml" type="spawnabletypes" />
	</ce>
	<ce folder="mod_ce">
		<file name="loot_boost_types.xml" type="types" />
		<file name="mod_weapons_types.xml" type="types" />
		<file name="mod_weapons_spawnabletypes.xml" type="spawnabletypes" />
		<file name="mod_optics_types.xml" type="types" />
	</ce>

</economycore>